Metadata-Version: 1.0
Name: jokesPythonModule
Version: 2.0.0
Summary: This Module is used to fetch a random joke from the server
Home-page: UNKNOWN
Author: Gautam Sagar Mallela
Author-email: gautamsagar.mallela@gmail.com
License: UNKNOWN
Platform: UNKNOWN
